xunitparserx.py
xunitparserx-1.9.12.data/data/trx-to-junit.xslt
xunitparserx-1.9.12.dist-info/AUTHORS
xunitparserx-1.9.12.dist-info/LICENSE
xunitparserx-1.9.12.dist-info/METADATA
xunitparserx-1.9.12.dist-info/WHEEL
xunitparserx-1.9.12.dist-info/top_level.txt
xunitparserx-1.9.12.dist-info/RECORD
