Metadata-Version: 2.1
Name: xunitparserx
Version: 1.9.12
Summary: Read JUnit/XUnit/MSTest XML files and map them to Python objects
Home-page: https://github.com/medlab/xunitparserx
Author: Laurent Bachelier, Cong Zhang
Author-email: laurent@bachelier.name, congzhangzh@gmail.com
Maintainer: Cong Zhang
Maintainer-email: congzhangzh@gmail.com
License: UNKNOWN
Platform: UNKNOWN
Classifier: License :: OSI Approved :: MIT License
Classifier: Programming Language :: Python :: 2.7
Classifier: Programming Language :: Python :: 3.6
Classifier: Programming Language :: Python :: 3.7
Classifier: Topic :: Software Development :: Testing
Requires-Dist: lxml
Requires-Dist: pytest
